warpwallet/__init__.py
warpwallet/key_utils.py
warpwallet/utils.py
warpwallet/wallet.py
warpwallet-1.0.dist-info/DESCRIPTION.rst
warpwallet-1.0.dist-info/METADATA
warpwallet-1.0.dist-info/RECORD
warpwallet-1.0.dist-info/WHEEL
warpwallet-1.0.dist-info/metadata.json
warpwallet-1.0.dist-info/top_level.txt
