Metadata-Version: 2.0
Name: warpwallet
Version: 1.0
Summary: Implementation of WarpWallet in Python.
Home-page: https://github.com/arturoleon/warp-wallet-python
Author: Arturo Leon
Author-email: arturo@arturoleon.io
License: UNKNOWN
Platform: UNKNOWN
Classifier: Programming Language :: Python :: 2.7
Classifier: License :: OSI Approved :: MIT License
Classifier: Operating System :: OS Independent
Requires-Dist: ecdsa
Requires-Dist: pycrypto
Requires-Dist: scrypt
